{
  "draftId": "67-01",
  "tasks": {
    "T1": {
      "status": "DONE",
      "notes": "",
      "touchedFiles": [],
      "updatedAt": "2026-07-21T04:02:34.075Z"
    },
    "T2": {
      "status": "DONE",
      "notes": "",
      "touchedFiles": [],
      "updatedAt": "2026-07-21T04:02:34.257Z"
    },
    "T3": {
      "status": "DONE",
      "notes": "",
      "touchedFiles": [],
      "updatedAt": "2026-07-21T04:03:54.699Z"
    },
    "T4": {
      "status": "DONE",
      "notes": "",
      "touchedFiles": [],
      "updatedAt": "2026-07-21T04:04:20.624Z"
    }
  }
}
